odoo/addons/shopinvader_locomotive_impersonate/README.rst
odoo/addons/shopinvader_locomotive_impersonate/__init__.py
odoo/addons/shopinvader_locomotive_impersonate/__manifest__.py
odoo/addons/shopinvader_locomotive_impersonate/i18n/shopinvader_locomotive_impersonate.pot
odoo/addons/shopinvader_locomotive_impersonate/models/__init__.py
odoo/addons/shopinvader_locomotive_impersonate/models/shopinvader_partner.py
odoo/addons/shopinvader_locomotive_impersonate/readme/CONTRIBUTORS.rst
odoo/addons/shopinvader_locomotive_impersonate/readme/DESCRIPTION.rst
odoo/addons/shopinvader_locomotive_impersonate/security/res_groups.xml
odoo/addons/shopinvader_locomotive_impersonate/services/__init__.py
odoo/addons/shopinvader_locomotive_impersonate/services/customer.py
odoo/addons/shopinvader_locomotive_impersonate/static/description/index.html
odoo/addons/shopinvader_locomotive_impersonate/tests/__init__.py
odoo/addons/shopinvader_locomotive_impersonate/tests/test_impersonate.py
odoo/addons/shopinvader_locomotive_impersonate/views/res_partner_view.xml
odoo/addons/shopinvader_locomotive_impersonate/views/shopinvader_partner_view.xml
odoo14_addon_shopinvader_locomotive_impersonate-14.0.1.0.1.dist-info/METADATA
odoo14_addon_shopinvader_locomotive_impersonate-14.0.1.0.1.dist-info/WHEEL
odoo14_addon_shopinvader_locomotive_impersonate-14.0.1.0.1.dist-info/top_level.txt
odoo14_addon_shopinvader_locomotive_impersonate-14.0.1.0.1.dist-info/RECORD
